identity_number_validator/__init__.py
identity_number_validator/main.py
identity_number_validator/countries/__init__.py
identity_number_validator/countries/ecuador.py
identity_number_validator-0.0.5.dist-info/LICENSE
identity_number_validator-0.0.5.dist-info/METADATA
identity_number_validator-0.0.5.dist-info/WHEEL
identity_number_validator-0.0.5.dist-info/top_level.txt
identity_number_validator-0.0.5.dist-info/RECORD
