Metadata-Version: 2.1
Name: identity-number-validator
Version: 0.0.5
Summary: A package for validating identity numbers from different countries
Home-page: https://github.com/DavidArmendariz/identity-number-validator-python
Author: David Armendariz
Author-email: davidarmendariz1998@gmail.com
License: UNKNOWN
Keywords: identity,cedula,ecuador
Platform: UNKNOWN
Classifier: Programming Language :: Python :: 3
Classifier: License :: OSI Approved :: MIT License
Classifier: Operating System :: OS Independent
Requires-Python: >=3.6
